main.py
wayspiritmcp_tpa-0.1.3.dist-info/METADATA
wayspiritmcp_tpa-0.1.3.dist-info/WHEEL
wayspiritmcp_tpa-0.1.3.dist-info/entry_points.txt
wayspiritmcp_tpa-0.1.3.dist-info/top_level.txt
wayspiritmcp_tpa-0.1.3.dist-info/RECORD
