Metadata-Version: 2.4
Name: wayspiritmcp-tpa
Version: 0.1.3
Summary: tpa test
Requires-Python: >=3.13
Requires-Dist: httpx>=0.28.1
Requires-Dist: mcp>=1.20.0
Requires-Dist: openai>=2.6.1
Requires-Dist: python-dotenv>=1.2.1
